basics/MUX/2to1.v
// 2:1 mux using gates
module mux_2to1 (
    input  A, 
    input  B,
    input select,
    output out
);

  wire w1, w2, w3;
  and (w1, A,~select);
  and (w2,B,select);
  or (out, w1, w2);
endmodule

basics/MUX/2to1_tb.v
`timescale 1ns/1ns
`include "2to1.v"


module mux2_1;

    reg A, B, select;
    wire out;    

mux_2to1 uut(.A(A), .B(B), .select(select), .out(out));


initial 
    begin
        $dumpfile("2 to 1.vcd");
        $dumpvars(0, mux2_1);
    end

initial begin
    $display("Start of simulation");
    
   $monitor("Time = %0d | A = %b | B = %b | select = %b | out = %b ", $time, A, B, select, out);
        
        // Test cases
        A = 0; B = 0; select = 0; #10; 
        A = 0; B = 1; select = 0; #10; 
        A = 1; B = 0; select = 0; #10; 
        A = 1; B = 1; select = 0; #10;
        A = 0; B = 0; select = 1; #10;
        A = 0; B = 1; select = 1; #10;
        A = 1; B = 0; select = 1; #10;
        A = 1; B = 1; select = 1; #10;
        
    $finish;
end

endmodule

basics/MUX/2 to 1.vcd
$date
	Sun Sep 01 21:09:48 2024
$end
$version
	Icarus Verilog
$end
$timescale
	1ns
$end
$scope module mux2_1 $end
$var wire 1 ! out $end
$var reg 1 " A $end
$var reg 1 # B $end
$var reg 1 $ select $end
$scope module uut $end
$var wire 1 " A $end
$var wire 1 # B $end
$var wire 1 ! out $end
$var wire 1 $ select $end
$var wire 1 % w1 $end
$var wire 1 & w2 $end
$upscope $end
$upscope $end
$enddefinitions $end
$comment Show the parameter values. $end
$dumpall
$end
#0
$dumpvars
0&
0%
0$
0#
0"
0!
$end
#10
1#
#20
1!
1%
0#
1"
#30
1#
#40
0!
0%
1$
0#
0"
#50
1!
1&
1#
#60
0!
0&
0#
1"
#70
1!
1&
1#
