basics/full_adder/full_adder.v
// Making full_adder using gates

module fullAdder (
    input A, input B,input cin, output sum, output cout
    
);
  wire w1, w2, w3;
  xor (w1, A,B);
  xor (sum, w1,cin);
  
  and (w2, A,B);
  and (w3, cin, w1);
  or (cout, w3, w2);
endmodule

basics/full_adder/full_adder_tb.v
`timescale 1ns/1ns
`include "full_adder.v"


module full_adder_tb;

    reg A, B, cin;
    wire sum, cout;    

fullAdder uut(.A(A), .B(B), .cin(cin), .sum(sum), .cout(cout));


initial 
    begin
        $dumpfile("full_adder.vcd");
        $dumpvars(0, full_adder_tb);
    end

initial begin
    $display("Start of simulation");
    
   $monitor("Time = %0d | A = %b | B = %b | cin = %b | Sum = %b | Carry = %b", $time, A, B, cin, sum, cout);
        
        // Test cases
        A = 0; B = 0; cin = 0; #10; 
        A = 0; B = 1; cin = 0; #10; 
        A = 1; B = 0; cin = 0; #10; 
        A = 1; B = 1; cin = 0; #10;
        A = 0; B = 0; cin = 1; #10;
        A = 0; B = 1; cin = 1; #10;
        A = 1; B = 0; cin = 1; #10;
        A = 1; B = 1; cin = 1; #10;
        
    $finish;
end

endmodule

basics/full_adder/full_adder.vcd
$date
	Sun Sep 01 19:22:04 2024
$end
$version
	Icarus Verilog
$end
$timescale
	1ns
$end
$scope module full_adder_tb $end
$var wire 1 ! sum $end
$var wire 1 " cout $end
$var reg 1 # A $end
$var reg 1 $ B $end
$var reg 1 % cin $end
$scope module uut $end
$var wire 1 # A $end
$var wire 1 $ B $end
$var wire 1 % cin $end
$var wire 1 " cout $end
$var wire 1 ! sum $end
$var wire 1 & w1 $end
$var wire 1 ' w2 $end
$var wire 1 ( w3 $end
$upscope $end
$upscope $end
$enddefinitions $end
$comment Show the parameter values. $end
$dumpall
$end
#0
$dumpvars
0(
0'
0&
0%
0$
0#
0"
0!
$end
#10
1!
1&
1$
#20
0$
1#
#30
0!
1"
0&
1'
1$
#40
0"
1!
0'
1%
0$
0#
#50
1"
0!
1(
1&
1$
#60
0$
1#
#70
1!
0(
0&
1'
1$
